{"imageStack":{"representative":{"maxDimensions":{"width":"1984","height":"2825"},"images":{"l":{"dimensions":{"width":"1200","height":"1709"},"src":"AT_LGB_129_FR-none_2019_Overall-l.jpg","path":"01_Overall"},"xs":{"dimensions":{"width":"200","height":"285"},"src":"AT_LGB_129_FR-none_2019_Overall-xs.jpg","path":"01_Overall"},"s":{"dimensions":{"width":"300","height":"427"},"src":"AT_LGB_129_FR-none_2019_Overall-s.jpg","path":"01_Overall"},"m":{"dimensions":{"width":"800","height":"1139"},"src":"AT_LGB_129_FR-none_2019_Overall-m.jpg","path":"01_Overall"},"xl":{"dimensions":{"width":"1984","height":"2825"},"src":"AT_LGB_129_FR-none_2019_Overall-xl.jpg","path":"01_Overall"}}},"overall":{"maxDimensions":{"width":"1984","height":"2825"},"images":[{"l":{"dimensions":{"width":"1200","height":"1709"},"src":"AT_LGB_129_FR-none_2019_Overall-l.jpg","path":"01_Overall"},"xs":{"dimensions":{"width":"200","height":"285"},"src":"AT_LGB_129_FR-none_2019_Overall-xs.jpg","path":"01_Overall"},"s":{"dimensions":{"width":"300","height":"427"},"src":"AT_LGB_129_FR-none_2019_Overall-s.jpg","path":"01_Overall"},"m":{"dimensions":{"width":"800","height":"1139"},"src":"AT_LGB_129_FR-none_2019_Overall-m.jpg","path":"01_Overall"},"xl":{"dimensions":{"width":"1984","height":"2825"},"src":"AT_LGB_129_FR-none_2019_Overall-xl.jpg","path":"01_Overall"}}]},"reverse":{"maxDimensions":{"width":"3594","height":"4527"},"images":[{"l":{"dimensions":{"width":"1200","height":"1512"},"src":"AT_LGB_129_FR-none_2019_Reverse-l.jpg","path":"02_Reverse"},"xs":{"dimensions":{"width":"200","height":"252"},"src":"AT_LGB_129_FR-none_2019_Reverse-xs.jpg","path":"02_Reverse"},"s":{"dimensions":{"width":"300","height":"378"},"src":"AT_LGB_129_FR-none_2019_Reverse-s.jpg","path":"02_Reverse"},"m":{"dimensions":{"width":"800","height":"1008"},"src":"AT_LGB_129_FR-none_2019_Reverse-m.jpg","path":"02_Reverse"},"xl":{"dimensions":{"width":"3594","height":"4527"},"src":"AT_LGB_129_FR-none_2019_Reverse-xl.jpg","path":"02_Reverse"}}]},"irr":{"maxDimensions":[],"images":[]},"x-radiograph":{"maxDimensions":[],"images":[]},"uv-light":{"maxDimensions":[],"images":[]},"detail":{"maxDimensions":[],"images":[]},"photomicrograph":{"maxDimensions":[],"images":[]},"conservation":{"maxDimensions":[],"images":[]},"other":{"maxDimensions":[],"images":[]},"analysis":{"maxDimensions":[],"images":[]},"rkd":{"maxDimensions":[],"images":[]},"koe":{"maxDimensions":[],"images":[]},"reflected-light":{"maxDimensions":[],"images":[]},"transmitted-light":{"maxDimensions":[],"images":[]}}}