{"imageStack":{"representative":{"maxDimensions":{"width":"2002","height":"3100"},"images":{"l":{"dimensions":{"width":"1200","height":"1858"},"src":"DE_HABW_B101_FR-none_2010_Overall-l.jpg","path":"01_Overall"},"xs":{"dimensions":{"width":"200","height":"310"},"src":"DE_HABW_B101_FR-none_2010_Overall-xs.jpg","path":"01_Overall"},"s":{"dimensions":{"width":"300","height":"465"},"src":"DE_HABW_B101_FR-none_2010_Overall-s.jpg","path":"01_Overall"},"m":{"dimensions":{"width":"800","height":"1239"},"src":"DE_HABW_B101_FR-none_2010_Overall-m.jpg","path":"01_Overall"},"xl":{"dimensions":{"width":"2002","height":"3100"},"src":"DE_HABW_B101_FR-none_2010_Overall-xl.jpg","path":"01_Overall"}}},"overall":{"maxDimensions":{"width":"2002","height":"3100"},"images":[{"l":{"dimensions":{"width":"1200","height":"1720"},"src":"DE_HABW_B101_FR-none_2010_Overall-001-l.jpg","path":"01_Overall"},"xs":{"dimensions":{"width":"200","height":"287"},"src":"DE_HABW_B101_FR-none_2010_Overall-001-xs.jpg","path":"01_Overall"},"s":{"dimensions":{"width":"300","height":"430"},"src":"DE_HABW_B101_FR-none_2010_Overall-001-s.jpg","path":"01_Overall"},"m":{"dimensions":{"width":"800","height":"1147"},"src":"DE_HABW_B101_FR-none_2010_Overall-001-m.jpg","path":"01_Overall"},"xl":{"dimensions":{"width":"3234","height":"4636"},"src":"DE_HABW_B101_FR-none_2010_Overall-001-xl.jpg","path":"01_Overall"}},{"l":{"dimensions":{"width":"1200","height":"1858"},"src":"DE_HABW_B101_FR-none_2010_Overall-l.jpg","path":"01_Overall"},"xs":{"dimensions":{"width":"200","height":"310"},"src":"DE_HABW_B101_FR-none_2010_Overall-xs.jpg","path":"01_Overall"},"s":{"dimensions":{"width":"300","height":"465"},"src":"DE_HABW_B101_FR-none_2010_Overall-s.jpg","path":"01_Overall"},"m":{"dimensions":{"width":"800","height":"1239"},"src":"DE_HABW_B101_FR-none_2010_Overall-m.jpg","path":"01_Overall"},"xl":{"dimensions":{"width":"2002","height":"3100"},"src":"DE_HABW_B101_FR-none_2010_Overall-xl.jpg","path":"01_Overall"}}]},"reverse":{"maxDimensions":{"width":"3262","height":"4722"},"images":[{"l":{"dimensions":{"width":"1200","height":"1737"},"src":"DE_HABW_B101_FR-none_2010_Reverse-l.jpg","path":"02_Reverse"},"xs":{"dimensions":{"width":"200","height":"290"},"src":"DE_HABW_B101_FR-none_2010_Reverse-xs.jpg","path":"02_Reverse"},"s":{"dimensions":{"width":"300","height":"434"},"src":"DE_HABW_B101_FR-none_2010_Reverse-s.jpg","path":"02_Reverse"},"m":{"dimensions":{"width":"800","height":"1158"},"src":"DE_HABW_B101_FR-none_2010_Reverse-m.jpg","path":"02_Reverse"},"xl":{"dimensions":{"width":"3262","height":"4722"},"src":"DE_HABW_B101_FR-none_2010_Reverse-xl.jpg","path":"02_Reverse"}}]},"irr":{"maxDimensions":[],"images":[]},"x-radiograph":{"maxDimensions":[],"images":[]},"uv-light":{"maxDimensions":[],"images":[]},"detail":{"maxDimensions":[],"images":[]},"photomicrograph":{"maxDimensions":[],"images":[]},"conservation":{"maxDimensions":[],"images":[]},"other":{"maxDimensions":[],"images":[]},"analysis":{"maxDimensions":[],"images":[]},"rkd":{"maxDimensions":[],"images":[]},"koe":{"maxDimensions":[],"images":[]},"reflected-light":{"maxDimensions":[],"images":[]},"transmitted-light":{"maxDimensions":[],"images":[]}}}